magicregex/__init__.py
magicregex/core.py
magicregex-0.1.3.dist-info/LICENSE
magicregex-0.1.3.dist-info/METADATA
magicregex-0.1.3.dist-info/WHEEL
magicregex-0.1.3.dist-info/RECORD
