Metadata-Version: 2.1
Name: magicregex
Version: 0.1.3
Summary: Readable regular expressions in Python
Home-page: https://github.com/ThomasWollmann/magicregex-python
License: Apache 2.0
Author: Thomas Wollmann
Requires-Python: >=3.8,<4.0
Classifier: License :: Other/Proprietary License
Classifier: Programming Language :: Python :: 3
Classifier: Programming Language :: Python :: 3.8
Classifier: Programming Language :: Python :: 3.9
Classifier: Programming Language :: Python :: 3.10
Classifier: Programming Language :: Python :: 3.11
Classifier: Topic :: Software Development :: Libraries :: Python Modules
Requires-Dist: regex (>=2022.10.31,<2023.0.0)
Project-URL: Repository, https://github.com/ThomasWollmann/magicregex-python
